odoo/addons/mrp_bom_structure_html/README.rst
odoo/addons/mrp_bom_structure_html/__init__.py
odoo/addons/mrp_bom_structure_html/__manifest__.py
odoo/addons/mrp_bom_structure_html/i18n/mrp_bom_structure_html.pot
odoo/addons/mrp_bom_structure_html/static/description/icon.png
odoo/addons/mrp_bom_structure_html/views/mrp_bom_structure_report_view.xml
odoo11_addon_mrp_bom_structure_html-11.0.1.0.0.99.dev1.dist-info/METADATA
odoo11_addon_mrp_bom_structure_html-11.0.1.0.0.99.dev1.dist-info/RECORD
odoo11_addon_mrp_bom_structure_html-11.0.1.0.0.99.dev1.dist-info/WHEEL
odoo11_addon_mrp_bom_structure_html-11.0.1.0.0.99.dev1.dist-info/top_level.txt
